Metadata-Version: 2.1
Name: odoo-addon-product_pricelist_direct_print_company_group
Version: 18.0.1.0.0.2
Requires-Python: >=3.10
Requires-Dist: odoo-addon-base_partner_company_group==18.0.*
Requires-Dist: odoo-addon-product_pricelist_direct_print==18.0.*
Requires-Dist: odoo==18.0.*
Summary: Print Pricelist items using the company group model
Home-page: https://github.com/OCA/product-attribute
License: AGPL-3
Author: Tecnativa, Odoo Community Association (OCA)
Author-email: support@odoo-community.org
Classifier: Programming Language :: Python
Classifier: Framework :: Odoo
Classifier: Framework :: Odoo :: 18.0
Classifier: License :: OSI Approved :: GNU Affero General Public License v3
